{
	"realm": "cognito",
	"enabled": true,
	"displayName": "Cognito Emulator",
	"registrationAllowed": false,
	"resetPasswordAllowed": true,
	"editUsernameAllowed": false,
	"bruteForceProtected": false,
	"loginWithEmailAllowed": true,
	"duplicateEmailsAllowed": false,
	"verifyEmail": false,
	"clients": [
		{
			"clientId": "local_client",
			"name": "Local Development Client",
			"enabled": true,
			"redirectUris": ["http://localhost/*"],
			"webOrigins": ["*"],
			"directAccessGrantsEnabled": true,
			"serviceAccountsEnabled": false,
			"publicClient": true,
			"protocol": "openid-connect",
			"standardFlowEnabled": true,
			"implicitFlowEnabled": false,
			"fullScopeAllowed": false,
			"protocolMappers": [
				{
					"name": "cognito-groups-mapper",
					"protocol": "openid-connect",
					"protocolMapper": "oidc-group-membership-mapper",
					"consentRequired": false,
					"config": {
						"full.path": "false",
						"id.token.claim": "true",
						"access.token.claim": "true",
						"claim.name": "cognito:groups",
						"userinfo.token.claim": "true"
					}
				},
				{
					"name": "client-id-mapper",
					"protocol": "openid-connect",
					"protocolMapper": "oidc-hardcoded-claim-mapper",
					"consentRequired": false,
					"config": {
						"claim.value": "local_client",
						"id.token.claim": "true",
						"access.token.claim": "true",
						"claim.name": "client_id",
						"jsonType.label": "String"
					}
				}
			]
		}
	]
}
